README.md
imagespack.py
setup.py
imagespack.egg-info/PKG-INFO
imagespack.egg-info/SOURCES.txt
imagespack.egg-info/dependency_links.txt
imagespack.egg-info/entry_points.txt
imagespack.egg-info/requires.txt
imagespack.egg-info/top_level.txt